odoo/addons/account_menu/README.rst
odoo/addons/account_menu/__init__.py
odoo/addons/account_menu/__manifest__.py
odoo/addons/account_menu/demo/res_groups.xml
odoo/addons/account_menu/i18n/account_menu.pot
odoo/addons/account_menu/i18n/ca.po
odoo/addons/account_menu/i18n/da.po
odoo/addons/account_menu/i18n/fr.po
odoo/addons/account_menu/i18n/hr.po
odoo/addons/account_menu/i18n/it.po
odoo/addons/account_menu/i18n/pt.po
odoo/addons/account_menu/i18n/tr.po
odoo/addons/account_menu/readme/CONFIGURE.rst
odoo/addons/account_menu/readme/CONTRIBUTORS.rst
odoo/addons/account_menu/readme/DESCRIPTION.rst
odoo/addons/account_menu/readme/ROADMAP.rst
odoo/addons/account_menu/static/description/icon.png
odoo/addons/account_menu/static/description/index.html
odoo/addons/account_menu/views/menu.xml
odoo/addons/account_menu/views/view_account_bank_statement.xml
odoo/addons/account_menu/views/view_account_move_line.xml
odoo12_addon_account_menu-12.0.1.0.1.dist-info/METADATA
odoo12_addon_account_menu-12.0.1.0.1.dist-info/WHEEL
odoo12_addon_account_menu-12.0.1.0.1.dist-info/top_level.txt
odoo12_addon_account_menu-12.0.1.0.1.dist-info/RECORD
