Metadata-Version: 2.1
Name: odoo12-addon-account-menu
Version: 12.0.1.0.1
Summary: Adds missing menu entries for Account module
Home-page: https://github.com/OCA/account-financial-tools
Author: GRAP, Odoo Community Association (OCA)
Author-email: support@odoo-community.org
License: AGPL-3
Platform: UNKNOWN
Classifier: Programming Language :: Python
Classifier: Framework :: Odoo
Classifier: Framework :: Odoo :: 12.0
Classifier: License :: OSI Approved :: GNU Affero General Public License v3
Requires-Python: >=3.5
Requires-Dist: odoo12-addon-account-coa-menu
Requires-Dist: odoo12-addon-account-group-menu
Requires-Dist: odoo12-addon-account-tag-menu
Requires-Dist: odoo12-addon-account-type-menu
Requires-Dist: odoo <12.1dev,>=12.0a
